dfclient/__init__.py
dfclient/client.py
dfclient/exceptions.py
dfclient-0.0.5.dist-info/LICENSE
dfclient-0.0.5.dist-info/METADATA
dfclient-0.0.5.dist-info/WHEEL
dfclient-0.0.5.dist-info/top_level.txt
dfclient-0.0.5.dist-info/RECORD
