Metadata-Version: 2.1
Name: dfclient
Version: 0.0.5
Summary: data finance client
Home-page: https://github.com/greyfox-dev/dfclient
Author: RBC
Author-email: vlatish@rbc.ru
License: UNKNOWN
Platform: UNKNOWN
Classifier: Programming Language :: Python
Classifier: License :: Other/Proprietary License
Classifier: Operating System :: Unix
Requires-Python: >=3.6.0, <4
Requires-Dist: aiohttp
